optodetools/__init__.py
optodetools/core.py
optodetools/lut.py
optodetools-0.1.1.dist-info/LICENSE.txt
optodetools-0.1.1.dist-info/METADATA
optodetools-0.1.1.dist-info/WHEEL
optodetools-0.1.1.dist-info/top_level.txt
optodetools-0.1.1.dist-info/RECORD
