Metadata-Version: 2.1
Name: optodetools
Version: 0.1.1
Summary: A python library for simulating and correcting oxygen optode time response error
Home-page: https://github.com/cgrdn/optodetools
Author: Christopher Gordon
Author-email: chris.gordon@dfo-mpo.gc.ca
License: The MIT License (MIT)
Platform: UNKNOWN
Classifier: Programming Language :: Python :: 3.4
Classifier: Programming Language :: Python :: 3.5
Classifier: Programming Language :: Python :: 3.6
Classifier: Programming Language :: Python :: 3.7
Classifier: Programming Language :: Python :: 3.8
Classifier: Topic :: Scientific/Engineering
Classifier: Intended Audience :: Science/Research
Classifier: Operating System :: OS Independent
Classifier: Development Status :: 3 - Alpha
Requires-Python: >=3.4
License-File: LICENSE.txt
Requires-Dist: numpy
Requires-Dist: scipy
